metaidigittts/__init__.py
metaidigittts/main.py
metaidigittts-0.1.3.dist-info/METADATA
metaidigittts-0.1.3.dist-info/WHEEL
metaidigittts-0.1.3.dist-info/entry_points.txt
metaidigittts-0.1.3.dist-info/top_level.txt
metaidigittts-0.1.3.dist-info/RECORD
